[{"engine":"pmd","fileName":"C:\\Code Scanning Git\\TestingGitActions\\force-app\\main\\default\\classes\\DummyAccountClass.cls","violations":[{"line":6,"column":5,"endLine":6,"endColumn":11,"severity":3,"ruleName":"EmptyStatementBlock","category":"Error Prone","url":"https://docs.pmd-code.org/pmd-doc-7.4.0/pmd_rules_apex_errorprone.html#emptystatementblock","message":"\r\nAvoid empty block statements.\r\n"},{"line":6,"column":12,"endLine":8,"endColumn":6,"severity":3,"ruleName":"ApexDoc","category":"Documentation","url":"https://docs.pmd-code.org/pmd-doc-7.4.0/pmd_rules_apex_documentation.html#apexdoc","message":"\r\nMissing ApexDoc comment\r\n"}]}]