[{"engine":"pmd","fileName":"C:\\Code Scanning Git\\TestingGitActions\\force-app\\main\\default\\classes\\TestAccountClass.cls","violations":[{"line":1,"column":21,"endLine":18,"endColumn":2,"severity":3,"ruleName":"ApexDoc","category":"Documentation","url":"https://docs.pmd-code.org/pmd-doc-7.4.0/pmd_rules_apex_documentation.html#apexdoc","message":"\r\nMissing ApexDoc comment\r\n"},{"line":2,"column":5,"endLine":2,"endColumn":11,"severity":3,"ruleName":"EmptyStatementBlock","category":"Error Prone","url":"https://docs.pmd-code.org/pmd-doc-7.4.0/pmd_rules_apex_errorprone.html#emptystatementblock","message":"\r\nAvoid empty block statements.\r\n"},{"line":2,"column":12,"endLine":4,"endColumn":6,"severity":3,"ruleName":"ApexDoc","category":"Documentation","url":"https://docs.pmd-code.org/pmd-doc-7.4.0/pmd_rules_apex_documentation.html#apexdoc","message":"\r\nMissing ApexDoc comment\r\n"},{"line":5,"column":19,"endLine":12,"endColumn":6,"severity":3,"ruleName":"ApexDoc","category":"Documentation","url":"https://docs.pmd-code.org/pmd-doc-7.4.0/pmd_rules_apex_documentation.html#apexdoc","message":"\r\nMissing ApexDoc comment\r\n"},{"line":6,"column":9,"endLine":6,"endColumn":34,"severity":3,"ruleName":"AvoidDebugStatements","category":"Performance","url":"https://docs.pmd-code.org/pmd-doc-7.4.0/pmd_rules_apex_performance.html#avoiddebugstatements","message":"\r\nAvoid debug statements since they impact on performance\r\n"},{"line":6,"column":9,"endLine":6,"endColumn":34,"severity":3,"ruleName":"DebugsShouldUseLoggingLevel","category":"Best Practices","url":"https://docs.pmd-code.org/pmd-doc-7.4.0/pmd_rules_apex_bestpractices.html#debugsshoulduselogginglevel","message":"\r\nCalls to System.debug should specify a logging level.\r\n"},{"line":11,"column":9,"endLine":11,"endColumn":47,"severity":3,"ruleName":"AvoidDebugStatements","category":"Performance","url":"https://docs.pmd-code.org/pmd-doc-7.4.0/pmd_rules_apex_performance.html#avoiddebugstatements","message":"\r\nAvoid debug statements since they impact on performance\r\n"},{"line":11,"column":9,"endLine":11,"endColumn":47,"severity":3,"ruleName":"DebugsShouldUseLoggingLevel","category":"Best Practices","url":"https://docs.pmd-code.org/pmd-doc-7.4.0/pmd_rules_apex_bestpractices.html#debugsshoulduselogginglevel","message":"\r\nCalls to System.debug should specify a logging level.\r\n"},{"line":14,"column":19,"endLine":17,"endColumn":6,"severity":3,"ruleName":"ApexDoc","category":"Documentation","url":"https://docs.pmd-code.org/pmd-doc-7.4.0/pmd_rules_apex_documentation.html#apexdoc","message":"\r\nMissing ApexDoc comment\r\n"},{"line":15,"column":9,"endLine":15,"endColumn":52,"severity":3,"ruleName":"AvoidDebugStatements","category":"Performance","url":"https://docs.pmd-code.org/pmd-doc-7.4.0/pmd_rules_apex_performance.html#avoiddebugstatements","message":"\r\nAvoid debug statements since they impact on performance\r\n"},{"line":15,"column":9,"endLine":15,"endColumn":52,"severity":3,"ruleName":"DebugsShouldUseLoggingLevel","category":"Best Practices","url":"https://docs.pmd-code.org/pmd-doc-7.4.0/pmd_rules_apex_bestpractices.html#debugsshoulduselogginglevel","message":"\r\nCalls to System.debug should specify a logging level.\r\n"},{"line":16,"column":9,"endLine":16,"endColumn":52,"severity":3,"ruleName":"AvoidDebugStatements","category":"Performance","url":"https://docs.pmd-code.org/pmd-doc-7.4.0/pmd_rules_apex_performance.html#avoiddebugstatements","message":"\r\nAvoid debug statements since they impact on performance\r\n"},{"line":16,"column":9,"endLine":16,"endColumn":52,"severity":3,"ruleName":"DebugsShouldUseLoggingLevel","category":"Best Practices","url":"https://docs.pmd-code.org/pmd-doc-7.4.0/pmd_rules_apex_bestpractices.html#debugsshoulduselogginglevel","message":"\r\nCalls to System.debug should specify a logging level.\r\n"}]}]